nlptest/__init__.py
nlptest/nlptest.py
nlptest/testrunner.py
nlptest/augmentation/__init__.py
nlptest/data/config.yml
nlptest/data/BoolQ/bias.jsonl
nlptest/data/BoolQ/combined.jsonl
nlptest/data/BoolQ/dev-tiny.jsonl
nlptest/data/BoolQ/dev.jsonl
nlptest/data/BoolQ/test-tiny.jsonl
nlptest/data/BoolQ/test.jsonl
nlptest/data/HellaSwag/hellaswag-test-tiny.jsonl
nlptest/data/HellaSwag/hellaswag-test.jsonl
nlptest/data/MMLU/MMLU-test-tiny.jsonl
nlptest/data/MMLU/MMLU-test.jsonl
nlptest/data/NQ-open/combined.jsonl
nlptest/data/NQ-open/test-tiny.jsonl
nlptest/data/NQ-open/test.jsonl
nlptest/data/NarrativeQA/NarrativeQA-test-tiny.jsonl
nlptest/data/NarrativeQA/NarrativeQA-test.jsonl
nlptest/data/OpenBookQA/OpenBookQA-test-tiny.jsonl
nlptest/data/OpenBookQA/OpenBookQA-test.jsonl
nlptest/data/TruthfulQA/TruthfulQA-combined.jsonl
nlptest/data/TruthfulQA/TruthfulQA-test-tiny.jsonl
nlptest/data/TruthfulQA/TruthfulQA-test.jsonl
nlptest/data/Xsum/XSum-test-tiny.jsonl
nlptest/data/Xsum/XSum-test.jsonl
nlptest/data/Xsum/bias.jsonl
nlptest/data/config/ai21_config.yml
nlptest/data/config/azure_config.yml
nlptest/data/config/cohere_config.yml
nlptest/data/config/huggingface_config.yml
nlptest/data/config/openai_config.yml
nlptest/data/config/toxicity_config.yml
nlptest/data/conll/sample.conll
nlptest/data/imdb/sample.csv
nlptest/data/quac/Quac-test-tiny.jsonl
nlptest/data/quac/Quac-test.jsonl
nlptest/data/textcat_imdb/config.cfg
nlptest/data/textcat_imdb/meta.json
nlptest/data/textcat_imdb/tokenizer
nlptest/data/textcat_imdb/textcat/cfg
nlptest/data/textcat_imdb/textcat/model
nlptest/data/textcat_imdb/vocab/key2row
nlptest/data/textcat_imdb/vocab/lookups.bin
nlptest/data/textcat_imdb/vocab/strings.json
nlptest/data/textcat_imdb/vocab/vectors
nlptest/data/textcat_imdb/vocab/vectors.cfg
nlptest/data/toxicity/toxicity-test-tiny.jsonl
nlptest/datahandler/__init__.py
nlptest/datahandler/datasource.py
nlptest/datahandler/format.py
nlptest/modelhandler/__init__.py
nlptest-1.5.0.dist-info/LICENSE
nlptest-1.5.0.dist-info/METADATA
nlptest-1.5.0.dist-info/WHEEL
nlptest-1.5.0.dist-info/top_level.txt
nlptest-1.5.0.dist-info/RECORD
