Metadata-Version: 2.1
Name: nlptest
Version: 1.5.0
Summary: John Snow Labs provides a library for delivering safe & effective NLP models.
Home-page: https://www.nlptest.org
Author: John Snow Labs
Author-email: support@johnsnowlabs.com
Project-URL: Bug Reports, https://github.com/JohnSnowLabs/nlptest/issues
Project-URL: Source, https://github.com/JohnSnowLabs/nlptest/
Keywords: NLP testing robustness bias fairness representation accuracy
Classifier: Development Status :: 5 - Production/Stable
Classifier: Intended Audience :: Developers
Classifier: Topic :: Software Development :: Build Tools
Classifier: License :: OSI Approved :: Apache Software License
Classifier: Programming Language :: Python :: 3
Classifier: Programming Language :: Python :: 3.7
Classifier: Programming Language :: Python :: 3.8
Classifier: Programming Language :: Python :: 3.9
Classifier: Programming Language :: Python :: 3.10
Classifier: Programming Language :: Python :: 3.11
Requires-Python: >=3.7, <3.12
License-File: LICENSE
Requires-Dist: numpy
Requires-Dist: pandas
Requires-Dist: transformers (<=4.28.1)
Requires-Dist: torch
Requires-Dist: sentencepiece
Requires-Dist: pydantic
Requires-Dist: nest-asyncio
Requires-Dist: jsonlines
Requires-Dist: langchain
Requires-Dist: evaluate
Requires-Dist: rouge-score
Requires-Dist: typing-extensions (<4.6.0)
